{
  "invoice_number": "818188",
  "invoice_date": "05/08/25",
  "term_code": "2",
  "over_credit_limit": false,
  "warehouse": "01",
  "salesperson": "JV",
  "pick_ticket": "758905",
  "customer_code": "1653",
  "customer_name": "VARCO MA",
  "totals": {
    "expected_subtotal": 448.07,
    "cost": 260.08,
    "gm_percent": "42.0%",
    "tax": 26.88,
    "freight": 0.0,
    "discount": 0.0,
    "doc_total": 474.95,
    "calculated_subtotal": 448.07,
    "match": true
  },
  "items": [
    {
      "ln#": 1,
      "ITEM": "LCD100",
      "Description": "WIPES FOR GLASSES/BO",
      "units": 5.0,
      "UM": "BX",
      "PRICE": 5.95,
      "PRICE_OVERRIDE": true,
      "PRICE_UM": "BX",
      "COST": 3.8,
      "COST_UM": "BX",
      "extension": 29.75,
      "gm%": "36.1",
      "CLS": "500",
      "T": "Y",
      "M": "N",
      "I": "S",
      "R": "",
      "GL": "000",
      "COMM%": "",
      "SW": "01"
    },
    {
      "ln#": 2,
      "ITEM": "PUREAU",
      "Description": "16.9OZ. PURIFIED WAT",
      "units": 84.0,
      "UM": "CS",
      "PRICE": 4.98,
      "PRICE_OVERRIDE": true,
      "PRICE_UM": "CS",
      "COST": 2.87,
      "COST_UM": "CS",
      "extension": 418.32,
      "gm%": "42.4",
      "CLS": "500",
      "T": "Y",
      "M": "N",
      "I": "S",
      "R": "",
      "GL": "000",
      "COMM%": "",
      "SW": "01"
    }
  ]
}