{
  "invoice_number": "818333",
  "invoice_date": "05/08/25",
  "term_code": "2",
  "over_credit_limit": false,
  "warehouse": "01",
  "salesperson": "CA",
  "pick_ticket": "759202",
  "customer_code": "1422",
  "customer_name": "POTOMAC",
  "totals": {
    "expected_subtotal": 40.98,
    "cost": 29.78,
    "gm_percent": "27.3%",
    "tax": 2.46,
    "freight": 0.0,
    "discount": 0.0,
    "doc_total": 43.44,
    "calculated_subtotal": 40.98,
    "match": true
  },
  "items": [
    {
      "ln#": 1,
      "ITEM": "107563C",
      "Description": "WATER HOSE NOZZLE",
      "units": 1.0,
      "UM": "EA",
      "PRICE": 5.0,
      "PRICE_OVERRIDE": true,
      "PRICE_UM": "EA",
      "COST": 3.36,
      "COST_UM": "EA",
      "extension": 5.0,
      "gm%": "32.8",
      "CLS": "697",
      "T": "Y",
      "M": "N",
      "I": "S",
      "R": "",
      "GL": "000",
      "COMM%": ".0",
      "SW": "01"
    },
    {
      "ln#": 2,
      "ITEM": "175-D",
      "Description": "LOCK BRASS COMBINATI",
      "units": 2.0,
      "UM": "EA",
      "PRICE": 17.99,
      "PRICE_OVERRIDE": true,
      "PRICE_UM": "EA",
      "COST": 13.212,
      "COST_UM": "EA",
      "extension": 35.98,
      "gm%": "26.6",
      "CLS": "760",
      "T": "Y",
      "M": "N",
      "I": "S",
      "R": "",
      "GL": "000",
      "COMM%": ".0",
      "SW": "01"
    }
  ]
}