{
  "invoice_number": "818497",
  "invoice_date": "05/08/25",
  "term_code": "2",
  "over_credit_limit": false,
  "warehouse": "01",
  "salesperson": "JS",
  "pick_ticket": "759325",
  "customer_code": "1397",
  "customer_name": "ELECTRIC",
  "totals": {
    "expected_subtotal": 460.95,
    "cost": 173.33,
    "gm_percent": "62.4%",
    "tax": 27.66,
    "freight": 0.0,
    "discount": 0.0,
    "doc_total": 488.61,
    "calculated_subtotal": 460.95,
    "match": true
  },
  "items": [
    {
      "ln#": 1,
      "ITEM": "S-SN14",
      "Description": "1/4\"-20 SPRING NUT P",
      "units": 600.0,
      "UM": "EA",
      "PRICE": 0.6,
      "PRICE_OVERRIDE": true,
      "PRICE_UM": "EA",
      "COST": 0.208,
      "COST_UM": "EA",
      "extension": 360.0,
      "gm%": "65.3",
      "CLS": "231",
      "T": "Y",
      "M": "N",
      "I": "S",
      "R": "",
      "GL": "000",
      "COMM%": ".0",
      "SW": "01"
    },
    {
      "ln#": 2,
      "ITEM": "046004",
      "Description": "1/4\"X1\" FENDER WASHE",
      "units": 6.0,
      "UM": "C",
      "PRICE": 5.25,
      "PRICE_OVERRIDE": true,
      "PRICE_UM": "C",
      "COST": 2.0,
      "COST_UM": "C",
      "extension": 31.5,
      "gm%": "61.9",
      "CLS": "303",
      "T": "Y",
      "M": "N",
      "I": "S",
      "R": "",
      "GL": "000",
      "COMM%": ".0",
      "SW": "01"
    },
    {
      "ln#": 3,
      "ITEM": "001402",
      "Description": "1/4\"X1\" HEX BOLT GRA",
      "units": 6.0,
      "UM": "C",
      "PRICE": 9.0,
      "PRICE_OVERRIDE": true,
      "PRICE_UM": "C",
      "COST": 4.674,
      "COST_UM": "C",
      "extension": 54.0,
      "gm%": "48.1",
      "CLS": "303",
      "T": "Y",
      "M": "N",
      "I": "S",
      "R": "",
      "GL": "000",
      "COMM%": ".0",
      "SW": "01"
    },
    {
      "ln#": 4,
      "ITEM": "SN-119",
      "Description": "WINDEX SPRAY CLEANER",
      "units": 1.0,
      "UM": "EA",
      "PRICE": 6.95,
      "PRICE_OVERRIDE": true,
      "PRICE_UM": "EA",
      "COST": 4.422,
      "COST_UM": "EA",
      "extension": 6.95,
      "gm%": "36.4",
      "CLS": "752",
      "T": "Y",
      "M": "N",
      "I": "S",
      "R": "",
      "GL": "000",
      "COMM%": ".0",
      "SW": "01"
    },
    {
      "ln#": 5,
      "ITEM": "14-10075H",
      "Description": "#10X3/4\"HEX HEAD TEK",
      "units": 5.0,
      "UM": "C",
      "PRICE": 1.7,
      "PRICE_OVERRIDE": true,
      "PRICE_UM": "C",
      "COST": 57.046,
      "COST_UM": "CS",
      "extension": 8.5,
      "gm%": "52.1",
      "CLS": "304",
      "T": "Y",
      "M": "N",
      "I": "S",
      "R": "",
      "GL": "000",
      "COMM%": ".0",
      "SW": "01"
    }
  ]
}