{
  "invoice_number": "818171",
  "invoice_date": "05/08/25",
  "term_code": "2",
  "over_credit_limit": false,
  "warehouse": "01",
  "salesperson": "RPS",
  "pick_ticket": "758793",
  "customer_code": "1764W",
  "customer_name": "POWER SO",
  "totals": {
    "expected_subtotal": 110.0,
    "cost": 48.0,
    "gm_percent": "56.4%",
    "tax": 1.2,
    "freight": 0.0,
    "discount": 0.0,
    "doc_total": 111.2,
    "calculated_subtotal": 110.0,
    "match": true
  },
  "items": [
    {
      "ln#": 9,
      "ITEM": "MINOR",
      "Description": "MINOR PARTS & LUBRIC",
      "units": 1.0,
      "UM": "EA",
      "PRICE": 20.0,
      "PRICE_OVERRIDE": true,
      "PRICE_UM": "EA",
      "COST": 3.0,
      "COST_UM": "EA",
      "extension": 20.0,
      "gm%": "85.0",
      "CLS": "911",
      "T": "Y",
      "M": "N",
      "I": "U",
      "R": "",
      "GL": "000",
      "COMM%": ".0",
      "SW": "01"
    },
    {
      "ln#": 10,
      "ITEM": "LABOR601",
      "Description": "LABOR FOR REPAIR",
      "units": 1.0,
      "UM": "EA",
      "PRICE": 90.0,
      "PRICE_OVERRIDE": false,
      "PRICE_UM": "EA",
      "COST": 45.0,
      "COST_UM": "EA",
      "extension": 90.0,
      "gm%": "50.0",
      "CLS": "900",
      "T": "N",
      "M": "N",
      "I": "U",
      "R": "",
      "GL": "LAB",
      "COMM%": ".0",
      "SW": "01"
    }
  ]
}