{
  "invoice_number": "818037",
  "invoice_date": "05/07/25",
  "term_code": "11",
  "over_credit_limit": false,
  "warehouse": "01",
  "salesperson": "JV",
  "pick_ticket": "758883",
  "customer_code": "55",
  "customer_name": "DYNALECT",
  "totals": {
    "expected_subtotal": 274.5,
    "cost": 240.61,
    "gm_percent": "12.3%",
    "tax": 16.47,
    "freight": 0.0,
    "discount": 0.0,
    "doc_total": 290.97,
    "calculated_subtotal": 198.0,
    "match": false
  },
  "items": [
    {
      "ln#": 4,
      "ITEM": "3453-20",
      "Description": "M12V FUEL 1/4\" HEX I",
      "units": 1.0,
      "UM": "EA",
      "PRICE": 129.0,
      "PRICE_OVERRIDE": false,
      "PRICE_UM": "EA",
      "COST": 105.997,
      "COST_UM": "EA",
      "extension": 129.0,
      "gm%": "17.8",
      "CLS": "850",
      "T": "Y",
      "M": "N",
      "I": "S",
      "R": "",
      "GL": "000",
      "COMM%": "",
      "SW": "01"
    },
    {
      "ln#": 5,
      "ITEM": "2367-20-F",
      "Description": "M12V ROVER FLOOD LIG",
      "units": 0.0,
      "UM": "EA",
      "PRICE": 69.0,
      "PRICE_OVERRIDE": true,
      "PRICE_UM": "EA",
      "COST": 33.0,
      "COST_UM": "EA",
      "extension": 0.0,
      "gm%": "0.0",
      "CLS": "856",
      "T": "Y",
      "M": "N",
      "I": "N",
      "R": "",
      "GL": "000",
      "COMM%": "",
      "SW": "01"
    },
    {
      "ln#": 7,
      "ITEM": "48-11-2425",
      "Description": "M12V HIGH OUTPUT BAT",
      "units": 1.0,
      "UM": "EA",
      "PRICE": 69.0,
      "PRICE_OVERRIDE": true,
      "PRICE_UM": "EA",
      "COST": 63.2,
      "COST_UM": "EA",
      "extension": 69.0,
      "gm%": "8.4",
      "CLS": "851",
      "T": "Y",
      "M": "N",
      "I": "S",
      "R": "",
      "GL": "000",
      "COMM%": "",
      "SW": "01"
    },
    {
      "ln#": 10,
      "ITEM": "4375950",
      "Description": "PRM-6 3 PHASE WIRE S",
      "units": 0.0,
      "UM": "EA",
      "PRICE": 205.0,
      "PRICE_OVERRIDE": true,
      "PRICE_UM": "EA",
      "COST": 180.59,
      "COST_UM": "EA",
      "extension": 0.0,
      "gm%": "0.0",
      "CLS": "705",
      "T": "Y",
      "M": "N",
      "I": "T",
      "R": "",
      "GL": "000",
      "COMM%": "",
      "SW": "01"
    }
  ]
}